ching.py
ching-1.3.1.dist-info/licenses/LICENSE
ching-1.3.1.dist-info/METADATA
ching-1.3.1.dist-info/WHEEL
ching-1.3.1.dist-info/top_level.txt
ching-1.3.1.dist-info/RECORD
