Metadata-Version: 2.4
Name: ching
Version: 1.3.1
Summary: A simple money management library
Author-email: Graham <terpstragraham@gmail.com>
License: BSD-3-Clause
License-File: LICENSE
Dynamic: license-file
